genvarloader-0.19.1.dist-info/METADATA
genvarloader-0.19.1.dist-info/WHEEL
genvarloader-0.19.1.dist-info/licenses/LICENSE.txt
genvarloader/__init__.py
genvarloader/_bigwig.py
genvarloader/_dataset/__init__.py
genvarloader/_dataset/_genotypes.py
genvarloader/_dataset/_impl.py
genvarloader/_dataset/_indexing.py
genvarloader/_dataset/_intervals.py
genvarloader/_dataset/_rag_variants.py
genvarloader/_dataset/_reconstruct.py
genvarloader/_dataset/_reference.py
genvarloader/_dataset/_tracks.py
genvarloader/_dataset/_utils.py
genvarloader/_dataset/_write.py
genvarloader/_dummy.py
genvarloader/_fasta.py
genvarloader/_ragged.py
genvarloader/_torch.py
genvarloader/_types.py
genvarloader/_utils.py
genvarloader/_variants/__init__.py
genvarloader/_variants/_records.py
genvarloader/_variants/_sitesonly.py
genvarloader/_variants/_utils.py
genvarloader/data_registry.py
genvarloader/genvarloader.abi3.so
genvarloader/genvarloader.pyi
genvarloader/py.typed
genvarloader-0.19.1.dist-info/RECORD
