Metadata-Version: 2.4
Name: genvarloader
Version: 0.19.1
Requires-Dist: numba>=0.58.1
Requires-Dist: loguru
Requires-Dist: attrs
Requires-Dist: natsort
Requires-Dist: polars>=1.30
Requires-Dist: cyvcf2
Requires-Dist: pandera
Requires-Dist: pysam
Requires-Dist: pyarrow
Requires-Dist: pyranges
Requires-Dist: pydantic>=2,<3
Requires-Dist: more-itertools
Requires-Dist: tqdm
Requires-Dist: pybigwig
Requires-Dist: einops
Requires-Dist: tbb
Requires-Dist: joblib
Requires-Dist: pooch
Requires-Dist: awkward
Requires-Dist: hirola>=0.3,<0.4
Requires-Dist: seqpro>=0.9
Requires-Dist: genoray>=1.0.1,<2
License-File: LICENSE.txt
Summary: Pipeline for efficient genomic data processing.
Author-email: David Laub <dlaub@ucsd.edu>, Aaron Ho <aho@salk.edu>
Requires-Python: >=3.10, <3.13
Project-URL: source, https://github.com/mcvickerlab/GenVarLoader
Project-URL: documentation, https://genvarloader.readthedocs.io/en/stable/
Project-URL: issues, https://github.com/mcvickerlab/GenVarLoader/issues
